{"Timestamp":"2020-09-17T12:04:31.7962968-03:00","Level":"Information","MessageTemplate":"Auditoria de Lectura: {@Type}, {@Header}, {@Body}","Properties":{"Type":"CONSULTA PRODUCTOS","Header":{"_typeTag":"LogHeader","TMSINSERT":"2020-09-17T12:04:30.9789904-03:00","CODSIGLA":"SMRT","TIORGINT":"","IDORGINTE":"","TXTTERMINAL":"192.168.12.160","CODLEGAJO":"jengagement@axxon365d.onmicrosoft.com","PERMISOSDEVISUALIZACION":["Administrador del sistema","Customer service app access","Sales, Enterprise app access"],"DISPOSITIVOMOVIL":false,"ENTORNO":"https://arlab005.ar.axxonconsulting.com/bff/api","GUIDUSUARIO":"{A0EC1193-1BE3-EA11-A815-000D3AC08736}","ACCION":"Consulta Productos"},"Body":{"_typeTag":"LogDataCuenta","IDCLIENTE":"","NROPRODUCTO":null,"TIPOCUENTA":null,"SERVICIO":null},"ApplicationName":"SMART","Version":"3.0.0"}}
{"Timestamp":"2020-09-17T12:04:52.1280679-03:00","Level":"Information","MessageTemplate":"Auditoria de Lectura: {@Type}, {@Header}, {@Body}","Properties":{"Type":"CONSULTA PRODUCTOS","Header":{"_typeTag":"LogHeader","TMSINSERT":"2020-09-17T12:04:51.6738865-03:00","CODSIGLA":"SMRT","TIORGINT":"","IDORGINTE":"","TXTTERMINAL":"192.168.12.160","CODLEGAJO":"jengagement@axxon365d.onmicrosoft.com","PERMISOSDEVISUALIZACION":["Administrador del sistema","Customer service app access","Sales, Enterprise app access"],"DISPOSITIVOMOVIL":false,"ENTORNO":"https://arlab005.ar.axxonconsulting.com/bff/api","GUIDUSUARIO":"{A0EC1193-1BE3-EA11-A815-000D3AC08736}","ACCION":"Consulta Productos"},"Body":{"_typeTag":"LogDataCuenta","IDCLIENTE":"","NROPRODUCTO":null,"TIPOCUENTA":null,"SERVICIO":null},"ApplicationName":"SMART","Version":"3.0.0"}}
{"Timestamp":"2020-09-17T12:04:52.2051400-03:00","Level":"Information","MessageTemplate":"Auditoria de Lectura: {@Type}, {@Header}, {@Body}","Properties":{"Type":"CONSULTA INVERSIONES","Header":{"_typeTag":"LogHeader","TMSINSERT":"2020-09-17T12:04:51.6898127-03:00","CODSIGLA":"SMRT","TIORGINT":"","IDORGINTE":"","TXTTERMINAL":"192.168.12.160","CODLEGAJO":"jengagement@axxon365d.onmicrosoft.com","PERMISOSDEVISUALIZACION":["Administrador del sistema","Customer service app access","Sales, Enterprise app access"],"DISPOSITIVOMOVIL":false,"ENTORNO":"https://arlab005.ar.axxonconsulting.com/bff/api","GUIDUSUARIO":"{A0EC1193-1BE3-EA11-A815-000D3AC08736}","ACCION":"Consulta Inversiones"},"Body":{"_typeTag":"LogDataCuenta","IDCLIENTE":"","NROPRODUCTO":null,"TIPOCUENTA":null,"SERVICIO":null},"ApplicationName":"SMART","Version":"3.0.0"}}
{"Timestamp":"2020-09-17T12:05:06.0691611-03:00","Level":"Information","MessageTemplate":"Auditoria de Lectura: {@Type}, {@Header}, {@Body}","Properties":{"Type":"CONSULTA INVERSIONES","Header":{"_typeTag":"LogHeader","TMSINSERT":"2020-09-17T12:05:05.7808866-03:00","CODSIGLA":"SMRT","TIORGINT":"","IDORGINTE":"","TXTTERMINAL":"192.168.12.160","CODLEGAJO":"jengagement@axxon365d.onmicrosoft.com","PERMISOSDEVISUALIZACION":["Administrador del sistema","Customer service app access","Sales, Enterprise app access"],"DISPOSITIVOMOVIL":false,"ENTORNO":"https://arlab005.ar.axxonconsulting.com/bff/api","GUIDUSUARIO":"{A0EC1193-1BE3-EA11-A815-000D3AC08736}","ACCION":"Consulta Inversiones"},"Body":{"_typeTag":"LogDataCuenta","IDCLIENTE":"","NROPRODUCTO":null,"TIPOCUENTA":null,"SERVICIO":null},"ApplicationName":"SMART","Version":"3.0.0"}}
{"Timestamp":"2020-09-17T12:05:08.5400190-03:00","Level":"Information","MessageTemplate":"Auditoria de Lectura: {@Type}, {@Header}, {@Body}","Properties":{"Type":"CONSULTA PRODUCTOS","Header":{"_typeTag":"LogHeader","TMSINSERT":"2020-09-17T12:05:08.0846381-03:00","CODSIGLA":"SMRT","TIORGINT":"","IDORGINTE":"","TXTTERMINAL":"192.168.12.160","CODLEGAJO":"jengagement@axxon365d.onmicrosoft.com","PERMISOSDEVISUALIZACION":["Administrador del sistema","Customer service app access","Sales, Enterprise app access"],"DISPOSITIVOMOVIL":false,"ENTORNO":"https://arlab005.ar.axxonconsulting.com/bff/api","GUIDUSUARIO":"{A0EC1193-1BE3-EA11-A815-000D3AC08736}","ACCION":"Consulta Productos"},"Body":{"_typeTag":"LogDataCuenta","IDCLIENTE":"","NROPRODUCTO":null,"TIPOCUENTA":null,"SERVICIO":null},"ApplicationName":"SMART","Version":"3.0.0"}}
{"Timestamp":"2020-09-17T12:10:46.6158703-03:00","Level":"Information","MessageTemplate":"Auditoria de Lectura: {@Type}, {@Header}, {@Body}","Properties":{"Type":"CONSULTA PRODUCTOS","Header":{"_typeTag":"LogHeader","TMSINSERT":"2020-09-17T12:10:46.3345848-03:00","CODSIGLA":"SMRT","TIORGINT":"","IDORGINTE":"","TXTTERMINAL":"192.168.12.160","CODLEGAJO":"jengagement@axxon365d.onmicrosoft.com","PERMISOSDEVISUALIZACION":["Administrador del sistema","Customer service app access","Sales, Enterprise app access"],"DISPOSITIVOMOVIL":false,"ENTORNO":"https://arlab005.ar.axxonconsulting.com/bff/api","GUIDUSUARIO":"{A0EC1193-1BE3-EA11-A815-000D3AC08736}","ACCION":"Consulta Productos"},"Body":{"_typeTag":"LogDataCuenta","IDCLIENTE":"","NROPRODUCTO":null,"TIPOCUENTA":null,"SERVICIO":null},"ApplicationName":"SMART","Version":"3.0.0"}}
{"Timestamp":"2020-09-17T12:10:52.3103481-03:00","Level":"Information","MessageTemplate":"Auditoria de Lectura: {@Type}, {@Header}, {@Body}","Properties":{"Type":"CONSULTA PRODUCTOS","Header":{"_typeTag":"LogHeader","TMSINSERT":"2020-09-17T12:10:51.7634736-03:00","CODSIGLA":"SMRT","TIORGINT":"","IDORGINTE":"","TXTTERMINAL":"192.168.12.160","CODLEGAJO":"jengagement@axxon365d.onmicrosoft.com","PERMISOSDEVISUALIZACION":["Administrador del sistema","Customer service app access","Sales, Enterprise app access"],"DISPOSITIVOMOVIL":false,"ENTORNO":"https://arlab005.ar.axxonconsulting.com/bff/api","GUIDUSUARIO":"{A0EC1193-1BE3-EA11-A815-000D3AC08736}","ACCION":"Consulta Productos"},"Body":{"_typeTag":"LogDataCuenta","IDCLIENTE":"","NROPRODUCTO":null,"TIPOCUENTA":null,"SERVICIO":null},"ApplicationName":"SMART","Version":"3.0.0"}}
{"Timestamp":"2020-09-17T12:21:31.7225326-03:00","Level":"Information","MessageTemplate":"Auditoria de Lectura: {@Type}, {@Header}, {@Body}","Properties":{"Type":"CONSULTA PRODUCTOS","Header":{"_typeTag":"LogHeader","TMSINSERT":"2020-09-17T12:21:30.4893975-03:00","CODSIGLA":"SMRT","TIORGINT":"","IDORGINTE":"","TXTTERMINAL":"192.168.12.160","CODLEGAJO":"jengagement@axxon365d.onmicrosoft.com","PERMISOSDEVISUALIZACION":["Administrador del sistema","Customer service app access","Sales, Enterprise app access"],"DISPOSITIVOMOVIL":false,"ENTORNO":"https://arlab005.ar.axxonconsulting.com/bff/api","GUIDUSUARIO":"{A0EC1193-1BE3-EA11-A815-000D3AC08736}","ACCION":"Consulta Productos"},"Body":{"_typeTag":"LogDataCuenta","IDCLIENTE":"","NROPRODUCTO":null,"TIPOCUENTA":null,"SERVICIO":null},"ApplicationName":"SMART","Version":"3.0.0"}}
{"Timestamp":"2020-09-17T12:21:42.7036463-03:00","Level":"Information","MessageTemplate":"Auditoria de Lectura: {@Type}, {@Header}, {@Body}","Properties":{"Type":"CONSULTA PRODUCTOS","Header":{"_typeTag":"LogHeader","TMSINSERT":"2020-09-17T12:21:42.4129346-03:00","CODSIGLA":"SMRT","TIORGINT":"","IDORGINTE":"","TXTTERMINAL":"192.168.12.160","CODLEGAJO":"jengagement@axxon365d.onmicrosoft.com","PERMISOSDEVISUALIZACION":["Administrador del sistema","Customer service app access","Sales, Enterprise app access"],"DISPOSITIVOMOVIL":false,"ENTORNO":"https://arlab005.ar.axxonconsulting.com/bff/api","GUIDUSUARIO":"{A0EC1193-1BE3-EA11-A815-000D3AC08736}","ACCION":"Consulta Productos"},"Body":{"_typeTag":"LogDataCuenta","IDCLIENTE":"","NROPRODUCTO":null,"TIPOCUENTA":null,"SERVICIO":null},"ApplicationName":"SMART","Version":"3.0.0"}}
{"Timestamp":"2020-09-17T12:34:33.5463253-03:00","Level":"Information","MessageTemplate":"Auditoria de Lectura: {@Type}, {@Header}, {@Body}","Properties":{"Type":"CONSULTA PRODUCTOS","Header":{"_typeTag":"LogHeader","TMSINSERT":"2020-09-17T12:34:31.8847635-03:00","CODSIGLA":"SMRT","TIORGINT":"","IDORGINTE":"","TXTTERMINAL":"192.168.12.160","CODLEGAJO":"jengagement@axxon365d.onmicrosoft.com","PERMISOSDEVISUALIZACION":["Administrador del sistema","Customer service app access","Sales, Enterprise app access"],"DISPOSITIVOMOVIL":false,"ENTORNO":"https://arlab005.ar.axxonconsulting.com/bff/api","GUIDUSUARIO":"{A0EC1193-1BE3-EA11-A815-000D3AC08736}","ACCION":"Consulta Productos"},"Body":{"_typeTag":"LogDataCuenta","IDCLIENTE":"","NROPRODUCTO":null,"TIPOCUENTA":null,"SERVICIO":null},"ApplicationName":"SMART","Version":"3.0.0"}}
{"Timestamp":"2020-09-17T13:24:46.7694561-03:00","Level":"Information","MessageTemplate":"Auditoria de Lectura: {@Type}, {@Header}, {@Body}","Properties":{"Type":"CONSULTA PRODUCTOS","Header":{"_typeTag":"LogHeader","TMSINSERT":"2020-09-17T13:24:46.0118273-03:00","CODSIGLA":"SMRT","TIORGINT":"","IDORGINTE":"","TXTTERMINAL":"192.168.12.160","CODLEGAJO":"jengagement@axxon365d.onmicrosoft.com","PERMISOSDEVISUALIZACION":["Administrador del sistema","Customer service app access","Sales, Enterprise app access"],"DISPOSITIVOMOVIL":false,"ENTORNO":"https://arlab005.ar.axxonconsulting.com/bff/api","GUIDUSUARIO":"{A0EC1193-1BE3-EA11-A815-000D3AC08736}","ACCION":"Consulta Productos"},"Body":{"_typeTag":"LogDataCuenta","IDCLIENTE":"","NROPRODUCTO":null,"TIPOCUENTA":null,"SERVICIO":null},"ApplicationName":"SMART","Version":"3.0.0"}}
{"Timestamp":"2020-09-17T13:25:18.2907831-03:00","Level":"Information","MessageTemplate":"Auditoria de Lectura: {@Type}, {@Header}, {@Body}","Properties":{"Type":"CONSULTA INVERSIONES","Header":{"_typeTag":"LogHeader","TMSINSERT":"2020-09-17T13:25:17.9939191-03:00","CODSIGLA":"SMRT","TIORGINT":"","IDORGINTE":"","TXTTERMINAL":"192.168.12.160","CODLEGAJO":"jengagement@axxon365d.onmicrosoft.com","PERMISOSDEVISUALIZACION":["Administrador del sistema","Customer service app access","Sales, Enterprise app access"],"DISPOSITIVOMOVIL":false,"ENTORNO":"https://arlab005.ar.axxonconsulting.com/bff/api","GUIDUSUARIO":"{A0EC1193-1BE3-EA11-A815-000D3AC08736}","ACCION":"Consulta Inversiones"},"Body":{"_typeTag":"LogDataCuenta","IDCLIENTE":"","NROPRODUCTO":null,"TIPOCUENTA":null,"SERVICIO":null},"ApplicationName":"SMART","Version":"3.0.0"}}
{"Timestamp":"2020-09-17T13:25:19.9243587-03:00","Level":"Information","MessageTemplate":"Auditoria de Lectura: {@Type}, {@Header}, {@Body}","Properties":{"Type":"CONSULTA PRODUCTOS","Header":{"_typeTag":"LogHeader","TMSINSERT":"2020-09-17T13:25:19.6540756-03:00","CODSIGLA":"SMRT","TIORGINT":"","IDORGINTE":"","TXTTERMINAL":"192.168.12.160","CODLEGAJO":"jengagement@axxon365d.onmicrosoft.com","PERMISOSDEVISUALIZACION":["Administrador del sistema","Customer service app access","Sales, Enterprise app access"],"DISPOSITIVOMOVIL":false,"ENTORNO":"https://arlab005.ar.axxonconsulting.com/bff/api","GUIDUSUARIO":"{A0EC1193-1BE3-EA11-A815-000D3AC08736}","ACCION":"Consulta Productos"},"Body":{"_typeTag":"LogDataCuenta","IDCLIENTE":"","NROPRODUCTO":null,"TIPOCUENTA":null,"SERVICIO":null},"ApplicationName":"SMART","Version":"3.0.0"}}
{"Timestamp":"2020-09-17T13:25:57.8625186-03:00","Level":"Information","MessageTemplate":"Auditoria de Lectura: {@Type}, {@Header}, {@Body}","Properties":{"Type":"CONSULTA PRODUCTOS","Header":{"_typeTag":"LogHeader","TMSINSERT":"2020-09-17T13:25:57.5812370-03:00","CODSIGLA":"SMRT","TIORGINT":"","IDORGINTE":"","TXTTERMINAL":"192.168.12.160","CODLEGAJO":"jengagement@axxon365d.onmicrosoft.com","PERMISOSDEVISUALIZACION":["Administrador del sistema","Customer service app access","Sales, Enterprise app access"],"DISPOSITIVOMOVIL":false,"ENTORNO":"https://arlab005.ar.axxonconsulting.com/bff/api","GUIDUSUARIO":"{A0EC1193-1BE3-EA11-A815-000D3AC08736}","ACCION":"Consulta Productos"},"Body":{"_typeTag":"LogDataCuenta","IDCLIENTE":"","NROPRODUCTO":null,"TIPOCUENTA":null,"SERVICIO":null},"ApplicationName":"SMART","Version":"3.0.0"}}
{"Timestamp":"2020-09-17T13:39:22.1651258-03:00","Level":"Information","MessageTemplate":"Auditoria de Lectura: {@Type}, {@Header}, {@Body}","Properties":{"Type":"CONSULTA PRODUCTOS","Header":{"_typeTag":"LogHeader","TMSINSERT":"2020-09-17T13:39:21.6808219-03:00","CODSIGLA":"SMRT","TIORGINT":"","IDORGINTE":"","TXTTERMINAL":"192.168.12.160","CODLEGAJO":"jengagement@axxon365d.onmicrosoft.com","PERMISOSDEVISUALIZACION":["Administrador del sistema","Customer service app access","Sales, Enterprise app access"],"DISPOSITIVOMOVIL":false,"ENTORNO":"https://arlab005.ar.axxonconsulting.com/bff/api","GUIDUSUARIO":"{A0EC1193-1BE3-EA11-A815-000D3AC08736}","ACCION":"Consulta Productos"},"Body":{"_typeTag":"LogDataCuenta","IDCLIENTE":"","NROPRODUCTO":null,"TIPOCUENTA":null,"SERVICIO":null},"ApplicationName":"SMART","Version":"3.0.0"}}
{"Timestamp":"2020-09-17T13:39:35.1424818-03:00","Level":"Information","MessageTemplate":"Auditoria de Lectura: {@Type}, {@Header}, {@Body}","Properties":{"Type":"CONSULTA PRODUCTOS","Header":{"_typeTag":"LogHeader","TMSINSERT":"2020-09-17T13:39:34.8605245-03:00","CODSIGLA":"SMRT","TIORGINT":"","IDORGINTE":"","TXTTERMINAL":"192.168.12.160","CODLEGAJO":"jengagement@axxon365d.onmicrosoft.com","PERMISOSDEVISUALIZACION":["Administrador del sistema","Customer service app access","Sales, Enterprise app access"],"DISPOSITIVOMOVIL":false,"ENTORNO":"https://arlab005.ar.axxonconsulting.com/bff/api","GUIDUSUARIO":"{A0EC1193-1BE3-EA11-A815-000D3AC08736}","ACCION":"Consulta Productos"},"Body":{"_typeTag":"LogDataCuenta","IDCLIENTE":"","NROPRODUCTO":null,"TIPOCUENTA":null,"SERVICIO":null},"ApplicationName":"SMART","Version":"3.0.0"}}
{"Timestamp":"2020-09-17T13:39:46.8037173-03:00","Level":"Information","MessageTemplate":"Auditoria de Lectura: {@Type}, {@Header}, {@Body}","Properties":{"Type":"CONSULTA INVERSIONES","Header":{"_typeTag":"LogHeader","TMSINSERT":"2020-09-17T13:39:46.5380940-03:00","CODSIGLA":"SMRT","TIORGINT":"","IDORGINTE":"","TXTTERMINAL":"192.168.12.160","CODLEGAJO":"jengagement@axxon365d.onmicrosoft.com","PERMISOSDEVISUALIZACION":["Administrador del sistema","Customer service app access","Sales, Enterprise app access"],"DISPOSITIVOMOVIL":false,"ENTORNO":"https://arlab005.ar.axxonconsulting.com/bff/api","GUIDUSUARIO":"{A0EC1193-1BE3-EA11-A815-000D3AC08736}","ACCION":"Consulta Inversiones"},"Body":{"_typeTag":"LogDataCuenta","IDCLIENTE":"","NROPRODUCTO":null,"TIPOCUENTA":null,"SERVICIO":null},"ApplicationName":"SMART","Version":"3.0.0"}}
{"Timestamp":"2020-09-17T13:40:31.5546284-03:00","Level":"Information","MessageTemplate":"Auditoria de Lectura: {@Type}, {@Header}, {@Body}","Properties":{"Type":"CONSULTA PRODUCTOS","Header":{"_typeTag":"LogHeader","TMSINSERT":"2020-09-17T13:40:31.0859146-03:00","CODSIGLA":"SMRT","TIORGINT":"","IDORGINTE":"","TXTTERMINAL":"192.168.12.160","CODLEGAJO":"jengagement@axxon365d.onmicrosoft.com","PERMISOSDEVISUALIZACION":["Administrador del sistema","Customer service app access","Sales, Enterprise app access"],"DISPOSITIVOMOVIL":false,"ENTORNO":"https://arlab005.ar.axxonconsulting.com/bff/api","GUIDUSUARIO":"{A0EC1193-1BE3-EA11-A815-000D3AC08736}","ACCION":"Consulta Productos"},"Body":{"_typeTag":"LogDataCuenta","IDCLIENTE":"","NROPRODUCTO":null,"TIPOCUENTA":null,"SERVICIO":null},"ApplicationName":"SMART","Version":"3.0.0"}}
{"Timestamp":"2020-09-17T14:22:07.8373691-03:00","Level":"Information","MessageTemplate":"Auditoria de Lectura: {@Type}, {@Header}, {@Body}","Properties":{"Type":"CONSULTA PRODUCTOS","Header":{"_typeTag":"LogHeader","TMSINSERT":"2020-09-17T14:22:07.0682968-03:00","CODSIGLA":"SMRT","TIORGINT":"","IDORGINTE":"","TXTTERMINAL":"192.168.12.160","CODLEGAJO":"jengagement@axxon365d.onmicrosoft.com","PERMISOSDEVISUALIZACION":["Administrador del sistema","Customer service app access","Sales, Enterprise app access"],"DISPOSITIVOMOVIL":false,"ENTORNO":"https://arlab005.ar.axxonconsulting.com/bff/api","GUIDUSUARIO":"{A0EC1193-1BE3-EA11-A815-000D3AC08736}","ACCION":"Consulta Productos"},"Body":{"_typeTag":"LogDataCuenta","IDCLIENTE":"","NROPRODUCTO":null,"TIPOCUENTA":null,"SERVICIO":null},"ApplicationName":"SMART","Version":"3.0.0"}}
{"Timestamp":"2020-09-17T14:22:07.8373691-03:00","Level":"Information","MessageTemplate":"Auditoria de Lectura: {@Type}, {@Header}, {@Body}","Properties":{"Type":"CONSULTA INVERSIONES","Header":{"_typeTag":"LogHeader","TMSINSERT":"2020-09-17T14:22:07.0682968-03:00","CODSIGLA":"SMRT","TIORGINT":"","IDORGINTE":"","TXTTERMINAL":"192.168.12.160","CODLEGAJO":"jengagement@axxon365d.onmicrosoft.com","PERMISOSDEVISUALIZACION":["Administrador del sistema","Customer service app access","Sales, Enterprise app access"],"DISPOSITIVOMOVIL":false,"ENTORNO":"https://arlab005.ar.axxonconsulting.com/bff/api","GUIDUSUARIO":"{A0EC1193-1BE3-EA11-A815-000D3AC08736}","ACCION":"Consulta Inversiones"},"Body":{"_typeTag":"LogDataCuenta","IDCLIENTE":"","NROPRODUCTO":null,"TIPOCUENTA":null,"SERVICIO":null},"ApplicationName":"SMART","Version":"3.0.0"}}
{"Timestamp":"2020-09-17T14:22:52.4624812-03:00","Level":"Information","MessageTemplate":"Auditoria de Lectura: {@Type}, {@Header}, {@Body}","Properties":{"Type":"CONSULTA PRODUCTOS","Header":{"_typeTag":"LogHeader","TMSINSERT":"2020-09-17T14:22:51.8999562-03:00","CODSIGLA":"SMRT","TIORGINT":"","IDORGINTE":"","TXTTERMINAL":"192.168.12.160","CODLEGAJO":"jengagement@axxon365d.onmicrosoft.com","PERMISOSDEVISUALIZACION":["Administrador del sistema","Customer service app access","Sales, Enterprise app access"],"DISPOSITIVOMOVIL":false,"ENTORNO":"https://arlab005.ar.axxonconsulting.com/bff/api","GUIDUSUARIO":"{A0EC1193-1BE3-EA11-A815-000D3AC08736}","ACCION":"Consulta Productos"},"Body":{"_typeTag":"LogDataCuenta","IDCLIENTE":"","NROPRODUCTO":null,"TIPOCUENTA":null,"SERVICIO":null},"ApplicationName":"SMART","Version":"3.0.0"}}
{"Timestamp":"2020-09-17T15:18:49.2708047-03:00","Level":"Information","MessageTemplate":"Auditoria de Lectura: {@Type}, {@Header}, {@Body}","Properties":{"Type":"CONSULTA INVERSIONES","Header":{"_typeTag":"LogHeader","TMSINSERT":"2020-09-17T15:18:48.4739171-03:00","CODSIGLA":"SMRT","TIORGINT":"","IDORGINTE":"","TXTTERMINAL":"192.168.12.160","CODLEGAJO":"jengagement@axxon365d.onmicrosoft.com","PERMISOSDEVISUALIZACION":["Administrador del sistema","Customer service app access","Sales, Enterprise app access"],"DISPOSITIVOMOVIL":false,"ENTORNO":"https://arlab005.ar.axxonconsulting.com/bff/api","GUIDUSUARIO":"{A0EC1193-1BE3-EA11-A815-000D3AC08736}","ACCION":"Consulta Inversiones"},"Body":{"_typeTag":"LogDataCuenta","IDCLIENTE":"","NROPRODUCTO":null,"TIPOCUENTA":null,"SERVICIO":null},"ApplicationName":"SMART","Version":"3.0.0"}}
{"Timestamp":"2020-09-17T15:18:49.2551785-03:00","Level":"Information","MessageTemplate":"Auditoria de Lectura: {@Type}, {@Header}, {@Body}","Properties":{"Type":"CONSULTA PRODUCTOS","Header":{"_typeTag":"LogHeader","TMSINSERT":"2020-09-17T15:18:48.4739171-03:00","CODSIGLA":"SMRT","TIORGINT":"","IDORGINTE":"","TXTTERMINAL":"192.168.12.160","CODLEGAJO":"jengagement@axxon365d.onmicrosoft.com","PERMISOSDEVISUALIZACION":["Administrador del sistema","Customer service app access","Sales, Enterprise app access"],"DISPOSITIVOMOVIL":false,"ENTORNO":"https://arlab005.ar.axxonconsulting.com/bff/api","GUIDUSUARIO":"{A0EC1193-1BE3-EA11-A815-000D3AC08736}","ACCION":"Consulta Productos"},"Body":{"_typeTag":"LogDataCuenta","IDCLIENTE":"","NROPRODUCTO":null,"TIPOCUENTA":null,"SERVICIO":null},"ApplicationName":"SMART","Version":"3.0.0"}}
{"Timestamp":"2020-09-17T15:19:40.3298594-03:00","Level":"Information","MessageTemplate":"Auditoria de Lectura: {@Type}, {@Header}, {@Body}","Properties":{"Type":"CONSULTA PRODUCTOS","Header":{"_typeTag":"LogHeader","TMSINSERT":"2020-09-17T15:19:39.7187833-03:00","CODSIGLA":"SMRT","TIORGINT":"","IDORGINTE":"","TXTTERMINAL":"192.168.12.160","CODLEGAJO":"jengagement@axxon365d.onmicrosoft.com","PERMISOSDEVISUALIZACION":["Administrador del sistema","Customer service app access","Sales, Enterprise app access"],"DISPOSITIVOMOVIL":false,"ENTORNO":"https://arlab005.ar.axxonconsulting.com/bff/api","GUIDUSUARIO":"{A0EC1193-1BE3-EA11-A815-000D3AC08736}","ACCION":"Consulta Productos"},"Body":{"_typeTag":"LogDataCuenta","IDCLIENTE":"","NROPRODUCTO":null,"TIPOCUENTA":null,"SERVICIO":null},"ApplicationName":"SMART","Version":"3.0.0"}}
{"Timestamp":"2020-09-17T15:28:34.0976490-03:00","Level":"Information","MessageTemplate":"Auditoria de Lectura: {@Type}, {@Header}, {@Body}","Properties":{"Type":"CONSULTA PRODUCTOS","Header":{"_typeTag":"LogHeader","TMSINSERT":"2020-09-17T15:28:33.5114435-03:00","CODSIGLA":"SMRT","TIORGINT":"","IDORGINTE":"","TXTTERMINAL":"192.168.12.160","CODLEGAJO":"jengagement@axxon365d.onmicrosoft.com","PERMISOSDEVISUALIZACION":["Administrador del sistema","Customer service app access","Sales, Enterprise app access"],"DISPOSITIVOMOVIL":false,"ENTORNO":"https://arlab005.ar.axxonconsulting.com/bff/api","GUIDUSUARIO":"{A0EC1193-1BE3-EA11-A815-000D3AC08736}","ACCION":"Consulta Productos"},"Body":{"_typeTag":"LogDataCuenta","IDCLIENTE":"","NROPRODUCTO":null,"TIPOCUENTA":null,"SERVICIO":null},"ApplicationName":"SMART","Version":"3.0.0"}}
{"Timestamp":"2020-09-17T15:28:45.9996129-03:00","Level":"Information","MessageTemplate":"Auditoria de Lectura: {@Type}, {@Header}, {@Body}","Properties":{"Type":"CONSULTA PRODUCTOS","Header":{"_typeTag":"LogHeader","TMSINSERT":"2020-09-17T15:28:45.5781810-03:00","CODSIGLA":"SMRT","TIORGINT":"","IDORGINTE":"","TXTTERMINAL":"192.168.12.160","CODLEGAJO":"jengagement@axxon365d.onmicrosoft.com","PERMISOSDEVISUALIZACION":["Administrador del sistema","Customer service app access","Sales, Enterprise app access"],"DISPOSITIVOMOVIL":false,"ENTORNO":"https://arlab005.ar.axxonconsulting.com/bff/api","GUIDUSUARIO":"{A0EC1193-1BE3-EA11-A815-000D3AC08736}","ACCION":"Consulta Productos"},"Body":{"_typeTag":"LogDataCuenta","IDCLIENTE":"","NROPRODUCTO":null,"TIPOCUENTA":null,"SERVICIO":null},"ApplicationName":"SMART","Version":"3.0.0"}}
{"Timestamp":"2020-09-17T17:27:28.3290105-03:00","Level":"Information","MessageTemplate":"Auditoria de Lectura: {@Type}, {@Header}, {@Body}","Properties":{"Type":"CONSULTA PRODUCTOS","Header":{"_typeTag":"LogHeader","TMSINSERT":"2020-09-17T17:27:27.6238135-03:00","CODSIGLA":"SMRT","TIORGINT":"SU","IDORGINTE":"233","TXTTERMINAL":"192.168.12.160","CODLEGAJO":"igarbus@axxon365d.onmicrosoft.com","PERMISOSDEVISUALIZACION":["Administrador del sistema","Common Data Service User","Customer service app access","Sales, Enterprise app access"],"DISPOSITIVOMOVIL":false,"ENTORNO":"https://arlab005.ar.axxonconsulting.com/bff/api","GUIDUSUARIO":"{A6801015-022B-45CE-BB7A-D0F6463C9BCF}","ACCION":"Consulta Productos"},"Body":{"_typeTag":"LogDataCuenta","IDCLIENTE":"","NROPRODUCTO":null,"TIPOCUENTA":null,"SERVICIO":null},"ApplicationName":"SMART","Version":"3.0.0"}}
{"Timestamp":"2020-09-17T17:27:33.2633876-03:00","Level":"Information","MessageTemplate":"Auditoria de Lectura: {@Type}, {@Header}, {@Body}","Properties":{"Type":"CONSULTA PRODUCTOS","Header":{"_typeTag":"LogHeader","TMSINSERT":"2020-09-17T17:27:32.8076866-03:00","CODSIGLA":"SMRT","TIORGINT":"SU","IDORGINTE":"233","TXTTERMINAL":"192.168.12.160","CODLEGAJO":"igarbus@axxon365d.onmicrosoft.com","PERMISOSDEVISUALIZACION":["Administrador del sistema","Common Data Service User","Customer service app access","Sales, Enterprise app access"],"DISPOSITIVOMOVIL":false,"ENTORNO":"https://arlab005.ar.axxonconsulting.com/bff/api","GUIDUSUARIO":"{A6801015-022B-45CE-BB7A-D0F6463C9BCF}","ACCION":"Consulta Productos"},"Body":{"_typeTag":"LogDataCuenta","IDCLIENTE":"","NROPRODUCTO":null,"TIPOCUENTA":null,"SERVICIO":null},"ApplicationName":"SMART","Version":"3.0.0"}}
{"Timestamp":"2020-09-17T17:27:42.5699319-03:00","Level":"Information","MessageTemplate":"Auditoria de Lectura: {@Type}, {@Header}, {@Body}","Properties":{"Type":"CONSULTA PRODUCTOS","Header":{"_typeTag":"LogHeader","TMSINSERT":"2020-09-17T17:27:42.2709098-03:00","CODSIGLA":"SMRT","TIORGINT":"SU","IDORGINTE":"233","TXTTERMINAL":"192.168.12.160","CODLEGAJO":"igarbus@axxon365d.onmicrosoft.com","PERMISOSDEVISUALIZACION":["Administrador del sistema","Common Data Service User","Customer service app access","Sales, Enterprise app access"],"DISPOSITIVOMOVIL":false,"ENTORNO":"https://arlab005.ar.axxonconsulting.com/bff/api","GUIDUSUARIO":"{A6801015-022B-45CE-BB7A-D0F6463C9BCF}","ACCION":"Consulta Productos"},"Body":{"_typeTag":"LogDataCuenta","IDCLIENTE":"","NROPRODUCTO":null,"TIPOCUENTA":null,"SERVICIO":null},"ApplicationName":"SMART","Version":"3.0.0"}}
{"Timestamp":"2020-09-17T17:30:02.5665400-03:00","Level":"Information","MessageTemplate":"Auditoria de Lectura: {@Type}, {@Header}, {@Body}","Properties":{"Type":"CONSULTA PRODUCTOS","Header":{"_typeTag":"LogHeader","TMSINSERT":"2020-09-17T17:30:02.1522891-03:00","CODSIGLA":"SMRT","TIORGINT":"SU","IDORGINTE":"233","TXTTERMINAL":"192.168.12.160","CODLEGAJO":"igarbus@axxon365d.onmicrosoft.com","PERMISOSDEVISUALIZACION":["Administrador del sistema","Common Data Service User","Customer service app access","Sales, Enterprise app access"],"DISPOSITIVOMOVIL":false,"ENTORNO":"https://arlab005.ar.axxonconsulting.com/bff/api","GUIDUSUARIO":"{A6801015-022B-45CE-BB7A-D0F6463C9BCF}","ACCION":"Consulta Productos"},"Body":{"_typeTag":"LogDataCuenta","IDCLIENTE":"","NROPRODUCTO":null,"TIPOCUENTA":null,"SERVICIO":null},"ApplicationName":"SMART","Version":"3.0.0"}}
{"Timestamp":"2020-09-17T17:30:08.6362362-03:00","Level":"Information","MessageTemplate":"Auditoria de Lectura: {@Type}, {@Header}, {@Body}","Properties":{"Type":"CONSULTA PRODUCTOS","Header":{"_typeTag":"LogHeader","TMSINSERT":"2020-09-17T17:30:08.3663956-03:00","CODSIGLA":"SMRT","TIORGINT":"SU","IDORGINTE":"233","TXTTERMINAL":"192.168.12.160","CODLEGAJO":"igarbus@axxon365d.onmicrosoft.com","PERMISOSDEVISUALIZACION":["Administrador del sistema","Common Data Service User","Customer service app access","Sales, Enterprise app access"],"DISPOSITIVOMOVIL":false,"ENTORNO":"https://arlab005.ar.axxonconsulting.com/bff/api","GUIDUSUARIO":"{A6801015-022B-45CE-BB7A-D0F6463C9BCF}","ACCION":"Consulta Productos"},"Body":{"_typeTag":"LogDataCuenta","IDCLIENTE":"","NROPRODUCTO":null,"TIPOCUENTA":null,"SERVICIO":null},"ApplicationName":"SMART","Version":"3.0.0"}}
{"Timestamp":"2020-09-17T17:31:03.8699108-03:00","Level":"Information","MessageTemplate":"Auditoria de Lectura: {@Type}, {@Header}, {@Body}","Properties":{"Type":"CONSULTA PRODUCTOS","Header":{"_typeTag":"LogHeader","TMSINSERT":"2020-09-17T17:31:03.4046350-03:00","CODSIGLA":"SMRT","TIORGINT":"SU","IDORGINTE":"233","TXTTERMINAL":"192.168.12.160","CODLEGAJO":"igarbus@axxon365d.onmicrosoft.com","PERMISOSDEVISUALIZACION":["Administrador del sistema","Common Data Service User","Customer service app access","Sales, Enterprise app access"],"DISPOSITIVOMOVIL":false,"ENTORNO":"https://arlab005.ar.axxonconsulting.com/bff/api","GUIDUSUARIO":"{A6801015-022B-45CE-BB7A-D0F6463C9BCF}","ACCION":"Consulta Productos"},"Body":{"_typeTag":"LogDataCuenta","IDCLIENTE":"","NROPRODUCTO":null,"TIPOCUENTA":null,"SERVICIO":null},"ApplicationName":"SMART","Version":"3.0.0"}}
